mcthings_extra/__init__.py
mcthings_extra/_version.py
mcthings_extra/csv_points.py
mcthings_extra/entity.py
mcthings_extra/lorenzo.py
mcthings_extra/rainbow.py
mcthings_extra/schematic.py
mcthings_extra/spiral.py
mcthings_extra/stairs_snail.py
mcthings_extra/u_shaped_stairs.py
mcthings_extra/decorators/__init__.py
mcthings_extra/decorators/villager_decorator.py
mcthings_extra-0.0.17.dist-info/LICENSE
mcthings_extra-0.0.17.dist-info/METADATA
mcthings_extra-0.0.17.dist-info/WHEEL
mcthings_extra-0.0.17.dist-info/top_level.txt
mcthings_extra-0.0.17.dist-info/RECORD
