Metadata-Version: 2.1
Name: mcthings-extra
Version: 0.0.17
Summary: Additional Things for the McThings Python library
Home-page: https://github.com/juntosdesdecasa/mcthings_extra
Author: Alvaro del Castillo
Author-email: alvaro.delcastillo@gmail.com
License: ASL
Keywords: development library minecraft buildings games
Platform: UNKNOWN
Classifier: Environment :: Console
Classifier: Intended Audience :: Developers
Classifier: License :: OSI Approved :: Apache Software License
Classifier: Operating System :: OS Independent
Classifier: Programming Language :: Python
Classifier: Programming Language :: Python :: 3
Classifier: Topic :: Software Development
Requires-Python: >=3.4
Requires-Dist: mcpi (>=1.2.0)
Requires-Dist: mcthings (>=0.49.6)
Requires-Dist: pandas
Requires-Dist: nbt
